aiopathy-0.1.1.dist-info/METADATA
aiopathy-0.1.1.dist-info/WHEEL
aiopathy-0.1.1.dist-info/licenses/LICENSE
aiopathy/__init__.py
aiopathy/about.py
aiopathy/cli.py
aiopathy/gcs.py
aiopathy/py.typed
aiopathy-0.1.1.dist-info/RECORD
