Metadata-Version: 2.1
Name: aiopathy
Version: 0.1.1
Author-Email: justindujardin <justin@dujardinconsulting.com>, lesleslie <les@wedgwoodwebworks.com>
License: BSD-3-Clause
Requires-Python: >=3.11
Requires-Dist: smart-open>=6.3.0
Requires-Dist: typer<1.0.0,>=0.3.0
Requires-Dist: aiopath>=0.6.11
Requires-Dist: aiofiles>=23.1.0
Requires-Dist: aioboto3>=11.1.0; extra == "aws"
Requires-Dist: azure-storage-blob>=12.16.0; extra == "azure"
Requires-Dist: google-auth>=2.17.3; extra == "gcs"
Requires-Dist: gcloud-aio-storage>=8.2.0; extra == "gcs"
Requires-Dist: google-api-core>=2.11.0; extra == "gcs"
Provides-Extra: aws
Provides-Extra: azure
Provides-Extra: gcs
